orange3_fairness-1.0.2.data/data/help/orange3-fairness/.buildinfo
orange3_fairness-1.0.2.data/data/help/orange3-fairness/genindex.html
orange3_fairness-1.0.2.data/data/help/orange3-fairness/index.html
orange3_fairness-1.0.2.data/data/help/orange3-fairness/objects.inv
orange3_fairness-1.0.2.data/data/help/orange3-fairness/search.html
orange3_fairness-1.0.2.data/data/help/orange3-fairness/searchindex.js
orange3_fairness-1.0.2.data/data/help/orange3-fairness/_images/adversarial-debiasing-example.png
orange3_fairness-1.0.2.data/data/help/orange3-fairness/_images/adversarial-debiasing-no-tensorflow.png
orange3_fairness-1.0.2.data/data/help/orange3-fairness/_images/adversarial-debiasing.png
orange3_fairness-1.0.2.data/data/help/orange3-fairness/_images/as-fairness-data-example.png
orange3_fairness-1.0.2.data/data/help/orange3-fairness/_images/as-fairness-data.png
orange3_fairness-1.0.2.data/data/help/orange3-fairness/_images/dataset-bias-example.png
orange3_fairness-1.0.2.data/data/help/orange3-fairness/_images/dataset-bias.png
orange3_fairness-1.0.2.data/data/help/orange3-fairness/_images/dataset-bias1.png
orange3_fairness-1.0.2.data/data/help/orange3-fairness/_images/equal-odds-postprocessing-example.png
orange3_fairness-1.0.2.data/data/help/orange3-fairness/_images/models.png
orange3_fairness-1.0.2.data/data/help/orange3-fairness/_images/reweighing-dataset-example.png
orange3_fairness-1.0.2.data/data/help/orange3-fairness/_images/reweighing-preprocessor-example.png
orange3_fairness-1.0.2.data/data/help/orange3-fairness/_images/visualization.png
orange3_fairness-1.0.2.data/data/help/orange3-fairness/_sources/index.rst.txt
orange3_fairness-1.0.2.data/data/help/orange3-fairness/_sources/widgets/adversarial-debiasing.md.txt
orange3_fairness-1.0.2.data/data/help/orange3-fairness/_sources/widgets/as-fairness-data.md.txt
orange3_fairness-1.0.2.data/data/help/orange3-fairness/_sources/widgets/combine-preprocessors.md.txt
orange3_fairness-1.0.2.dist-info/licenses/LICENSE
orange3_fairness-1.0.2.dist-info/METADATA
orange3_fairness-1.0.2.dist-info/WHEEL
orange3_fairness-1.0.2.dist-info/entry_points.txt
orange3_fairness-1.0.2.dist-info/top_level.txt
orange3_fairness-1.0.2.dist-info/RECORD
