Metadata-Version: 2.4
Name: Orange3-Fairness
Version: 1.0.2
Summary: Orange3 add-on for fairness-aware machine learning.
Home-page: https://github.com/biolab/orange3-fairness
Author: Bioinformatics Laboratory, FRI UL
Author-email: info@biolab.si
Maintainer: Zan Mervic
License: GPL3+
Keywords: orange3 add-on,orange3 fairness
Classifier: Development Status :: 3 - Alpha
Classifier: Intended Audience :: Science/Research
Classifier: Programming Language :: Python :: 3 :: Only
Classifier: Operating System :: MacOS
Classifier: Operating System :: Microsoft :: Windows
Classifier: Operating System :: Unix
License-File: LICENSE
Requires-Dist: setuptools>=51.0.0
Requires-Dist: numpy>=1.24.0
Requires-Dist: Orange3>=3.37.0
Requires-Dist: aif360>=0.6.0
Provides-Extra: doc
Requires-Dist: sphinx; extra == "doc"
Requires-Dist: sphinx_rtd_theme; extra == "doc"
Requires-Dist: recommonmark; extra == "doc"
Dynamic: author
Dynamic: author-email
Dynamic: classifier
Dynamic: description
Dynamic: description-content-type
Dynamic: home-page
Dynamic: keywords
Dynamic: license
Dynamic: license-file
Dynamic: maintainer
Dynamic: provides-extra
Dynamic: requires-dist
Dynamic: summary
